Metadata-Version: 2.1
Name: GitToXApi
Version: 0.2.1
Summary: Enable creation and edition of xapi file from git source
Home-page: https://github.com/git4school/gitToXApi
Download-URL: https://github.com/git4school/gitToXApi/archive/refs/tags/v_0.2.tar.gz
Author: Git4School
Author-email: 
License: MIT
Keywords: XApi
Classifier: Development Status :: 3 - Alpha
Classifier: Intended Audience :: Developers
Classifier: Topic :: Software Development :: Build Tools
Classifier: License :: OSI Approved :: MIT License
Classifier: Programming Language :: Python :: 3
Classifier: Programming Language :: Python :: 3.4
Classifier: Programming Language :: Python :: 3.5
Classifier: Programming Language :: Python :: 3.6
License-File: LICENCE.txt
Requires-Dist: tincan
Requires-Dist: GitPython
